[
 {
  "DOI": "",
  "abstract": "",
  "author": [
   {
    "family": "Rheault",
    "given": "Francois"
   },
   {
    "family": "Roy",
    "given": "Maggie"
   },
   {
    "family": "Cunnane",
    "given": "Stephen"
   },
   {
    "family": "Descoteaux",
    "given": "Maxime"
   }
  ],
  "container-title": "bioRxiv",
  "image": "rheault2018bbundle.png",
  "issued": {
   "date-parts": [
    [
     "2018",
     2
    ]
   ]
  },
  "title": "Bundle-specific fornix reconstruction for dual-tracer PET-tractometry"
 },
]